gil_node_openai/__init__.py
gil_node_openai/openai_connector.py
gil_node_openai/openai_image_generator.py
gil_node_openai-0.1.0.dist-info/METADATA
gil_node_openai-0.1.0.dist-info/WHEEL
gil_node_openai-0.1.0.dist-info/entry_points.txt
gil_node_openai-0.1.0.dist-info/top_level.txt
gil_node_openai-0.1.0.dist-info/RECORD
